pytest_grunnur/__init__.py
pytest_grunnur/plugin.py
pytest_grunnur/py.typed
pytest_grunnur-0.3.0.dist-info/entry_points.txt
pytest_grunnur-0.3.0.dist-info/WHEEL
pytest_grunnur-0.3.0.dist-info/METADATA
pytest_grunnur-0.3.0.dist-info/licenses/LICENSE.md
pytest_grunnur-0.3.0.dist-info/RECORD
