Metadata-Version: 2.1
Name: pytest_grunnur
Version: 0.3.0
Summary: Py.Test plugin for Grunnur-based packages.
License: MIT
Author-email: Bogdan Opanchuk <bogdan@opanchuk.net>
Requires-Python: >=3.10
Requires-Dist: grunnur>=0.3
Requires-Dist: pytest>=6
Provides-Extra: docs
Requires-Dist: sphinx>=4; extra == "docs"
Requires-Dist: furo; extra == "docs"
Requires-Dist: setuptools-scm; extra == "docs"
Provides-Extra: lint
Requires-Dist: mypy>=1.4; extra == "lint"
Requires-Dist: ruff>=0.5; extra == "lint"
Provides-Extra: tests
Requires-Dist: pytest-cov; extra == "tests"
Project-URL: homepage, https://github.com/fjarri/pytest-grunnur
